lightmatchingengine/__init__.py
lightmatchingengine/lightmatchingengine.py
lightmatchingengine-2019.1.4.dist-info/LICENSE.txt
lightmatchingengine-2019.1.4.dist-info/METADATA
lightmatchingengine-2019.1.4.dist-info/WHEEL
lightmatchingengine-2019.1.4.dist-info/top_level.txt
lightmatchingengine-2019.1.4.dist-info/RECORD
